[
  {
    "id": "3",
    "name": "Kennedy Lane",
    "email": "mattis.Cras@nonenimMauris.net",
    "phone": "(542) 451-7038"
  },
  {
    "id": "6",
    "name": "Samuel Jackson",
    "email": "Jackson@magnis.org",
    "phone": "(789) 25-3720"
  },
  {
    "id": "7",
    "name": "Reuben Henry",
    "email": "pharetra.ut@dictum.co.uk",
    "phone": "(715) 598-5792"
  },
  {
    "id": "8",
    "name": "Simon Morton",
    "email": "dui.Fusce.diam@Donec.com",
    "phone": "(233) 738-2360"
  },
  {
    "id": "9",
    "name": "Thomas Lucas",
    "email": "nec@Nulla.com",
    "phone": "(704) 398-7993"
  },
  {
    "id": "10",
    "name": "Alec Howard",
    "email": "Donec.elementum@scelerisquescelerisquedui.net",
    "phone": "(748) 206-2688"
  },
  {
    "id": "Xdo5dS7JR7Itk64nuCYBr",
    "name": "Miorty Olbrayt",
    "email": "joker@scelerisquescelerisquedui.net",
    "phone": "(555) 404-2688"
  },
  {
    "id": "gdH7J0aBNvdjbovloGNsq",
    "name": "Genry Ford",
    "email": "Ford@scelerisquescelerisquedui.net",
    "phone": "(369) 404-2688"
  }
]